glide/__init__.py
glide/core.py
glide/extract.py
glide/filter.py
glide/flow.py
glide/load.py
glide/math.py
glide/pipelines.py
glide/sql.py
glide/sql_utils.py
glide/transform.py
glide/utils.py
glide/version.py
glide/extensions/__init__.py
glide/extensions/celery.py
glide/extensions/dask.py
glide/extensions/pandas.py
glide/extensions/rq.py
glide-0.4.1.dist-info/AUTHORS.rst
glide-0.4.1.dist-info/LICENSE
glide-0.4.1.dist-info/METADATA
glide-0.4.1.dist-info/WHEEL
glide-0.4.1.dist-info/top_level.txt
glide-0.4.1.dist-info/RECORD
