Metadata-Version: 2.1
Name: glide
Version: 0.4.1
Summary: Easy ETL
Home-page: https://github.com/kmatarese/glide
Author: Kurt Matarese
Author-email: none@none.com
Maintainer: Kurt Matarese
License: MIT
Platform: UNKNOWN
Classifier: Development Status :: 3 - Alpha
Classifier: License :: OSI Approved :: MIT License
Classifier: Programming Language :: Python :: 3
Requires-Python: >=3.6
License-File: LICENSE
License-File: AUTHORS.rst
Requires-Dist: consecution (~=0.2.0)
Requires-Dist: html5lib (~=1.0.1)
Requires-Dist: imapclient (~=2.2.0)
Requires-Dist: importlib-metadata (<2)
Requires-Dist: lxml (==4.*,>=4.4.2)
Requires-Dist: openpyxl (~=3.0.1)
Requires-Dist: pandas (~=1.3.5)
Requires-Dist: pyexcel (~=0.5.15)
Requires-Dist: pyexcel-xls (~=0.5.8)
Requires-Dist: pyexcel-xlsx (~=0.5.8)
Requires-Dist: pymysql (~=0.9.3)
Requires-Dist: python-dateutil (~=2.8.1)
Requires-Dist: pyyaml (~=5.3)
Requires-Dist: requests (~=2.22.0)
Requires-Dist: sqlalchemy (~=1.4.40)
Requires-Dist: tlbx (~=0.1.19)
Requires-Dist: xlrd (~=1.2.0)
Provides-Extra: celery
Requires-Dist: celery[redis] (==4.4.0) ; extra == 'celery'
Requires-Dist: kombu (==4.5.0) ; extra == 'celery'
Provides-Extra: complete
Requires-Dist: black ; extra == 'complete'
Requires-Dist: celery[redis] (==4.4.0) ; extra == 'complete'
Requires-Dist: dask[complete] (~=2020.12.0) ; extra == 'complete'
Requires-Dist: distributed (==2020.12.0) ; extra == 'complete'
Requires-Dist: fake-useragent (~=0.1.11) ; extra == 'complete'
Requires-Dist: jinja2 (<3.1) ; extra == 'complete'
Requires-Dist: kombu (==4.5.0) ; extra == 'complete'
Requires-Dist: m2r (~=0.2.1) ; extra == 'complete'
Requires-Dist: numpydoc (~=0.9.2) ; extra == 'complete'
Requires-Dist: pre-commit ; extra == 'complete'
Requires-Dist: pylint ; extra == 'complete'
Requires-Dist: pytest-redis (~=2.0.0) ; extra == 'complete'
Requires-Dist: pytest-xprocess (~=0.13.1) ; extra == 'complete'
Requires-Dist: pytest (~=5.3.2) ; extra == 'complete'
Requires-Dist: rq (~=1.5.0) ; extra == 'complete'
Requires-Dist: sphinx (~=2.3.1) ; extra == 'complete'
Requires-Dist: twine (~=3.1.1) ; extra == 'complete'
Requires-Dist: wheel ; extra == 'complete'
Provides-Extra: dask
Requires-Dist: dask[complete] (~=2020.12.0) ; extra == 'dask'
Requires-Dist: distributed (==2020.12.0) ; extra == 'dask'
Provides-Extra: dev
Requires-Dist: black ; extra == 'dev'
Requires-Dist: fake-useragent (~=0.1.11) ; extra == 'dev'
Requires-Dist: m2r (~=0.2.1) ; extra == 'dev'
Requires-Dist: numpydoc (~=0.9.2) ; extra == 'dev'
Requires-Dist: pre-commit ; extra == 'dev'
Requires-Dist: pylint ; extra == 'dev'
Requires-Dist: pytest (~=5.3.2) ; extra == 'dev'
Requires-Dist: pytest-redis (~=2.0.0) ; extra == 'dev'
Requires-Dist: pytest-xprocess (~=0.13.1) ; extra == 'dev'
Requires-Dist: sphinx (~=2.3.1) ; extra == 'dev'
Requires-Dist: twine (~=3.1.1) ; extra == 'dev'
Requires-Dist: jinja2 (<3.1) ; extra == 'dev'
Requires-Dist: wheel ; extra == 'dev'
Provides-Extra: rq
Requires-Dist: rq (~=1.5.0) ; extra == 'rq'
